rodeo_utils/__init__.py
rodeo_utils/rodeo2antismash.py
rodeo_utils/rodeo_utils.py
rodeo_utils-0.0.2.dist-info/LICENSE
rodeo_utils-0.0.2.dist-info/METADATA
rodeo_utils-0.0.2.dist-info/WHEEL
rodeo_utils-0.0.2.dist-info/top_level.txt
rodeo_utils-0.0.2.dist-info/RECORD
